pptx/__init__.py
pptx/action.py
pptx/api.py
pptx/exc.py
pptx/media.py
pptx/package.py
pptx/presentation.py
pptx/py.typed
pptx/shared.py
pptx/slide.py
pptx/spec.py
pptx/table.py
pptx/types.py
pptx/util.py
pptx/chart/__init__.py
pptx/chart/axis.py
pptx/chart/category.py
pptx/chart/chart.py
pptx/chart/data.py
pptx/chart/datalabel.py
pptx/chart/legend.py
pptx/chart/marker.py
pptx/chart/plot.py
pptx/chart/point.py
pptx/chart/series.py
pptx/chart/xlsx.py
pptx/chart/xmlwriter.py
pptx/dml/__init__.py
pptx/dml/chtfmt.py
pptx/dml/color.py
pptx/dml/effect.py
pptx/dml/fill.py
pptx/dml/line.py
pptx/enum/__init__.py
pptx/enum/action.py
pptx/enum/base.py
pptx/enum/chart.py
pptx/enum/dml.py
pptx/enum/lang.py
pptx/enum/shapes.py
pptx/enum/text.py
pptx/opc/__init__.py
pptx/opc/constants.py
pptx/opc/oxml.py
pptx/opc/package.py
pptx/opc/packuri.py
pptx/opc/serialized.py
pptx/opc/shared.py
pptx/opc/spec.py
pptx/oxml/__init__.py
pptx/oxml/action.py
pptx/oxml/coreprops.py
pptx/oxml/ns.py
pptx/oxml/presentation.py
pptx/oxml/simpletypes.py
pptx/oxml/slide.py
pptx/oxml/table.py
pptx/oxml/text.py
pptx/oxml/theme.py
pptx/oxml/xmlchemy.py
pptx/oxml/chart/__init__.py
pptx/oxml/chart/axis.py
pptx/oxml/chart/chart.py
pptx/oxml/chart/datalabel.py
pptx/oxml/chart/legend.py
pptx/oxml/chart/marker.py
pptx/oxml/chart/plot.py
pptx/oxml/chart/series.py
pptx/oxml/chart/shared.py
pptx/oxml/dml/__init__.py
pptx/oxml/dml/color.py
pptx/oxml/dml/fill.py
pptx/oxml/dml/line.py
pptx/oxml/shapes/__init__.py
pptx/oxml/shapes/autoshape.py
pptx/oxml/shapes/connector.py
pptx/oxml/shapes/graphfrm.py
pptx/oxml/shapes/groupshape.py
pptx/oxml/shapes/picture.py
pptx/oxml/shapes/shared.py
pptx/parts/__init__.py
pptx/parts/chart.py
pptx/parts/coreprops.py
pptx/parts/embeddedpackage.py
pptx/parts/image.py
pptx/parts/media.py
pptx/parts/presentation.py
pptx/parts/slide.py
pptx/shapes/__init__.py
pptx/shapes/autoshape.py
pptx/shapes/base.py
pptx/shapes/connector.py
pptx/shapes/freeform.py
pptx/shapes/graphfrm.py
python_pptx-1.0.1.dist-info/LICENSE
python_pptx-1.0.1.dist-info/METADATA
python_pptx-1.0.1.dist-info/WHEEL
python_pptx-1.0.1.dist-info/top_level.txt
python_pptx-1.0.1.dist-info/RECORD
